{"frame_id": 2815, "walking": "0", "video_id": "VID_20161007_131547_reduced", "bbs": [{"right": 0.13211, "bottom": 0.607335, "top": 0.370861, "recognized": false, "bb_big_enough": false, "class": "artwork", "left": 0.01293}, {"artwork_id": "attis_donatello", "right": 0.670632, "bottom": 0.72579, "top": 0.282891, "confidence": 828, "recognized": true, "bb_big_enough": true, "class": "artwork", "left": 0.346249}, {"bottom": 0.757412, "top": 0.583698, "right": 0.949345, "class": "person", "left": 0.873885}, {"bottom": 0.788127, "top": 0.572483, "right": 0.977793, "class": "person", "left": 0.91738}], "p_voice": "0"}