{"frame_id": 2841, "walking": "0", "video_id": "VID_20161007_131547_reduced", "bbs": [{"right": 0.145505, "bottom": 0.610948, "top": 0.377934, "recognized": false, "bb_big_enough": false, "class": "artwork", "left": 0.014069}, {"artwork_id": "attis_donatello", "right": 0.694335, "bottom": 0.733307, "top": 0.284998, "confidence": 851, "recognized": true, "bb_big_enough": true, "class": "artwork", "left": 0.35468}, {"bottom": 0.766107, "top": 0.583635, "right": 0.954688, "class": "person", "left": 0.874903}, {"bottom": 0.798397, "top": 0.571442, "right": 0.980242, "class": "person", "left": 0.916063}], "p_voice": "0"}