{"frame_id": 6054, "walking": "1", "video_id": "VID_20161007_131547_reduced", "bbs": [{"artwork_id": "san_giorgio_donatello", "right": 0.913109, "bottom": 0.542801, "top": 0.109174, "confidence": 20, "recognized": true, "bb_big_enough": true, "class": "artwork", "left": 0.661755}, {"right": 0.593433, "bottom": 0.645177, "top": 0.392111, "recognized": false, "bb_big_enough": false, "class": "artwork", "left": 0.399439}, {"bottom": 0.85975, "top": 0.484598, "right": 0.987916, "class": "person", "left": 0.83056}, {"bottom": 0.907338, "top": 0.529906, "right": 0.813039, "class": "person", "left": 0.588998}], "p_voice": "0"}