{"frame_id": 1693, "walking": "0", "video_id": "VID_20161007_131547_reduced", "bbs": [{"artwork_id": "san_giovanni_battista_michelozzo", "right": 0.980255, "bottom": 0.782094, "top": 0.132287, "confidence": 86, "recognized": true, "bb_big_enough": true, "class": "artwork", "left": 0.543411}, {"bottom": 0.866144, "top": 0.593178, "right": 0.102158, "class": "person", "left": 0.006237}, {"right": 0.494146, "bottom": 0.937927, "top": 0.635341, "recognized": false, "bb_big_enough": true, "class": "artwork", "left": 0.186486}], "p_voice": "0"}