{"frame_id": 2606, "walking": "0", "video_id": "VID_20161007_131547_reduced", "bbs": [{"artwork_id": "david_marmo_donatello", "right": 0.279773, "bottom": 0.643744, "top": 0.368419, "confidence": 140, "recognized": true, "bb_big_enough": true, "class": "artwork", "left": 0.075024}, {"artwork_id": "attis_donatello", "right": 0.699261, "bottom": 0.735822, "top": 0.302251, "confidence": 622, "recognized": true, "bb_big_enough": true, "class": "artwork", "left": 0.402275}, {"bottom": 0.730924, "top": 0.530457, "right": 0.096733, "class": "person", "left": 0.008935}], "p_voice": "0"}