{"frame_id": 1173, "walking": "1", "video_id": "VID_20161007_131547_reduced", "bbs": [{"artwork_id": "san_giovanni_battista_donatello", "right": 0.974351, "bottom": 0.721464, "top": 0.064108, "confidence": 201, "recognized": true, "bb_big_enough": true, "class": "artwork", "left": 0.5321}, {"right": 0.112552, "bottom": 0.753757, "top": 0.55609, "recognized": false, "bb_big_enough": false, "class": "artwork", "left": 0.019108}, {"right": 0.352615, "bottom": 0.903247, "top": 0.611548, "recognized": false, "bb_big_enough": true, "class": "artwork", "left": 0.101038}], "p_voice": "0"}