{"frame_id": 3666, "walking": "0", "video_id": "VID_20161007_131547_reduced", "bbs": [{"artwork_id": "san_giorgio_donatello", "right": 0.54168, "bottom": 0.58028, "top": 0.021019, "confidence": 409, "recognized": true, "bb_big_enough": true, "class": "artwork", "left": 0.087488}, {"artwork_id": "san_giovanni_battista_michelozzo", "right": 0.880398, "bottom": 0.901777, "top": 0.132992, "confidence": 269, "recognized": true, "bb_big_enough": true, "class": "artwork", "left": 0.438449}], "p_voice": "0"}