{"frame_id": 2840, "walking": "0", "video_id": "VID_20161007_131547_reduced", "bbs": [{"right": 0.143314, "bottom": 0.610461, "top": 0.378872, "recognized": false, "bb_big_enough": false, "class": "artwork", "left": 0.015463}, {"artwork_id": "attis_donatello", "right": 0.69371, "bottom": 0.734801, "top": 0.286696, "confidence": 850, "recognized": true, "bb_big_enough": true, "class": "artwork", "left": 0.356865}, {"bottom": 0.766724, "top": 0.586473, "right": 0.953315, "class": "person", "left": 0.87395}, {"bottom": 0.796454, "top": 0.575486, "right": 0.979719, "class": "person", "left": 0.915516}], "p_voice": "0"}