{"frame_id": 2957, "walking": "1", "video_id": "VID_20161007_131547_reduced", "bbs": [{"right": 0.137244, "bottom": 0.443148, "top": 0.058971, "recognized": false, "bb_big_enough": true, "class": "artwork", "left": 0.005353}, {"artwork_id": "san_giovanni_battista_michelozzo", "right": 0.809701, "bottom": 0.641818, "top": 0.316684, "confidence": 22, "recognized": true, "bb_big_enough": true, "class": "artwork", "left": 0.571811}, {"bottom": 0.722773, "top": 0.50804, "right": 0.509458, "class": "person", "left": 0.377947}], "p_voice": "0"}