{"frame_id": 2599, "walking": "0", "video_id": "VID_20161007_131547_reduced", "bbs": [{"artwork_id": "david_marmo_donatello", "right": 0.285535, "bottom": 0.641113, "top": 0.37087, "confidence": 133, "recognized": true, "bb_big_enough": true, "class": "artwork", "left": 0.079919}, {"artwork_id": "attis_donatello", "right": 0.702138, "bottom": 0.740495, "top": 0.302835, "confidence": 615, "recognized": true, "bb_big_enough": true, "class": "artwork", "left": 0.400446}, {"bottom": 0.729122, "top": 0.534816, "right": 0.095543, "class": "person", "left": 0.007194}], "p_voice": "0"}