{"frame_id": 6063, "walking": "1", "video_id": "VID_20161007_131547_reduced", "bbs": [{"artwork_id": "san_giorgio_donatello", "right": 0.791395, "bottom": 0.518145, "top": 0.145089, "confidence": 29, "recognized": true, "bb_big_enough": true, "class": "artwork", "left": 0.552217}, {"right": 0.468412, "bottom": 0.63629, "top": 0.381379, "recognized": false, "bb_big_enough": true, "class": "artwork", "left": 0.263918}, {"bottom": 0.881555, "top": 0.479623, "right": 0.940485, "class": "person", "left": 0.694821}], "p_voice": "0"}